{
  "annotations": {
    "list": [
      {
        "builtIn": 1,
        "datasource": { "type": "grafana", "uid": "-- Grafana --" },
        "enable": true,
        "hide": true,
        "iconColor": "rgba(0, 211, 255, 1)",
        "name": "Annotations & Alerts",
        "type": "dashboard"
      }
    ]
  },
  "editable": true,
  "fiscalYearStartMonth": 0,
  "graphTooltip": 1,
  "id": null,
  "links": [],
  "liveNow": false,
  "panels": [
    {
      "datasource": { "type": "prometheus", "uid": "${DS_PROMETHEUS}" },
      "description": "Current wallet DB dependency state.",
      "fieldConfig": {
        "defaults": {
          "color": { "mode": "thresholds" },
          "mappings": [
            {
              "options": {
                "0": { "color": "red", "index": 0, "text": "Wallet DB Down" },
                "1": { "color": "green", "index": 1, "text": "Wallet DB OK" }
              },
              "type": "value"
            }
          ],
          "max": 1,
          "min": 0,
          "thresholds": {
            "mode": "absolute",
            "steps": [
              { "color": "red", "value": null },
              { "color": "green", "value": 1 }
            ]
          }
        },
        "overrides": []
      },
      "gridPos": { "h": 8, "w": 8, "x": 0, "y": 0 },
      "id": 1,
      "options": {
        "colorMode": "background",
        "graphMode": "none",
        "justifyMode": "center",
        "orientation": "auto",
        "percentChangeColorMode": "standard",
        "reduceOptions": { "calcs": ["lastNotNull"], "fields": "", "values": false },
        "showPercentChange": false,
        "textMode": "auto",
        "wideLayout": true
      },
      "targets": [
        {
          "editorMode": "code",
          "expr": "max(wallet_dependency_state{dependency=\"postgres-wallet\"})",
          "instant": true,
          "legendFormat": "postgres-wallet",
          "range": false,
          "refId": "A"
        }
      ],
      "title": "Wallet Dependency State Now",
      "type": "stat"
    },
    {
      "datasource": { "type": "prometheus", "uid": "${DS_PROMETHEUS}" },
      "description": "Dependency failures grouped by dependency over the last 5 minutes.",
      "fieldConfig": {
        "defaults": {
          "color": { "mode": "palette-classic" },
          "custom": {
            "axisBorderShow": false,
            "axisCenteredZero": false,
            "axisColorMode": "text",
            "axisLabel": "events/sec",
            "axisPlacement": "auto",
            "barAlignment": 0,
            "drawStyle": "bars",
            "fillOpacity": 75,
            "gradientMode": "none",
            "hideFrom": { "legend": false, "tooltip": false, "viz": false },
            "lineWidth": 1,
            "scaleDistribution": { "type": "linear" },
            "showPoints": "never",
            "stacking": { "group": "A", "mode": "normal" }
          },
          "unit": "ops"
        },
        "overrides": []
      },
      "gridPos": { "h": 8, "w": 16, "x": 8, "y": 0 },
      "id": 2,
      "options": {
        "legend": {
          "calcs": ["lastNotNull"],
          "displayMode": "table",
          "placement": "bottom",
          "showLegend": true
        },
        "tooltip": { "mode": "multi", "sort": "desc" }
      },
      "targets": [
        {
          "editorMode": "code",
          "expr": "sum by (dependency) (rate(dependency_check_failures_total[5m]))",
          "legendFormat": "{{dependency}}",
          "range": true,
          "refId": "A"
        }
      ],
      "title": "Dependency Failure Rate (5m)",
      "type": "timeseries"
    },
    {
      "datasource": { "type": "prometheus", "uid": "${DS_PROMETHEUS}" },
      "description": "Wallet dependency state over time.",
      "fieldConfig": {
        "defaults": {
          "color": { "mode": "palette-classic" },
          "custom": {
            "axisBorderShow": false,
            "axisCenteredZero": false,
            "axisColorMode": "text",
            "axisPlacement": "auto",
            "drawStyle": "line",
            "fillOpacity": 10,
            "lineInterpolation": "stepAfter",
            "lineWidth": 2,
            "pointSize": 3,
            "scaleDistribution": { "type": "linear" },
            "showPoints": "never",
            "stacking": { "group": "A", "mode": "none" }
          },
          "max": 1,
          "min": 0
        },
        "overrides": []
      },
      "gridPos": { "h": 9, "w": 12, "x": 0, "y": 8 },
      "id": 3,
      "options": {
        "legend": {
          "calcs": ["lastNotNull"],
          "displayMode": "list",
          "placement": "bottom",
          "showLegend": true
        },
        "tooltip": { "mode": "single", "sort": "none" }
      },
      "targets": [
        {
          "editorMode": "code",
          "expr": "wallet_dependency_state{dependency=\"postgres-wallet\"}",
          "legendFormat": "{{dependency}}",
          "range": true,
          "refId": "A"
        }
      ],
      "title": "Wallet Dependency State Over Time",
      "type": "timeseries"
    },
    {
      "datasource": { "type": "prometheus", "uid": "${DS_PROMETHEUS}" },
      "description": "Root DB check failures over time.",
      "fieldConfig": {
        "defaults": {
          "color": { "mode": "palette-classic" },
          "custom": {
            "axisBorderShow": false,
            "axisCenteredZero": false,
            "axisColorMode": "text",
            "axisLabel": "events/sec",
            "axisPlacement": "auto",
            "barAlignment": 0,
            "drawStyle": "bars",
            "fillOpacity": 70,
            "gradientMode": "none",
            "hideFrom": { "legend": false, "tooltip": false, "viz": false },
            "lineWidth": 1,
            "scaleDistribution": { "type": "linear" },
            "showPoints": "never",
            "stacking": { "group": "A", "mode": "normal" }
          },
          "unit": "ops"
        },
        "overrides": []
      },
      "gridPos": { "h": 9, "w": 12, "x": 12, "y": 8 },
      "id": 4,
      "options": {
        "legend": {
          "calcs": ["lastNotNull"],
          "displayMode": "table",
          "placement": "bottom",
          "showLegend": true
        },
        "tooltip": { "mode": "multi", "sort": "desc" }
      },
      "targets": [
        {
          "editorMode": "code",
          "expr": "rate(wallet_db_check_failures_total[5m])",
          "legendFormat": "wallet_db_check_failures_total",
          "range": true,
          "refId": "A"
        },
        {
          "editorMode": "code",
          "expr": "rate(identity_db_check_failures_total[5m])",
          "legendFormat": "identity_db_check_failures_total",
          "range": true,
          "refId": "B"
        }
      ],
      "title": "Root DB Failure Signals (5m)",
      "type": "timeseries"
    },
    {
      "datasource": { "type": "prometheus", "uid": "${DS_PROMETHEUS}" },
      "description": "Upstream propagation into platform services and portals.",
      "fieldConfig": {
        "defaults": {
          "color": { "mode": "palette-classic" },
          "custom": {
            "axisBorderShow": false,
            "axisCenteredZero": false,
            "axisColorMode": "text",
            "axisLabel": "events/sec",
            "axisPlacement": "auto",
            "barAlignment": 0,
            "drawStyle": "bars",
            "fillOpacity": 75,
            "gradientMode": "none",
            "hideFrom": { "legend": false, "tooltip": false, "viz": false },
            "lineWidth": 1,
            "scaleDistribution": { "type": "linear" },
            "showPoints": "never",
            "stacking": { "group": "A", "mode": "normal" }
          },
          "unit": "ops"
        },
        "overrides": []
      },
      "gridPos": { "h": 10, "w": 24, "x": 0, "y": 17 },
      "id": 5,
      "options": {
        "legend": {
          "calcs": ["lastNotNull"],
          "displayMode": "table",
          "placement": "bottom",
          "showLegend": true
        },
        "tooltip": { "mode": "multi", "sort": "desc" }
      },
      "targets": [
        {
          "editorMode": "code",
          "expr": "rate(system_dependency_unready_total[5m])",
          "legendFormat": "system_dependency_unready_total",
          "range": true,
          "refId": "A"
        },
        {
          "editorMode": "code",
          "expr": "rate(ops_dependency_unready_total[5m])",
          "legendFormat": "ops_dependency_unready_total",
          "range": true,
          "refId": "B"
        },
        {
          "editorMode": "code",
          "expr": "rate(customer_portal_upstream_failures_total[5m])",
          "legendFormat": "customer_portal_upstream_failures_total",
          "range": true,
          "refId": "C"
        },
        {
          "editorMode": "code",
          "expr": "rate(admin_portal_upstream_failures_total[5m])",
          "legendFormat": "admin_portal_upstream_failures_total",
          "range": true,
          "refId": "D"
        }
      ],
      "title": "Propagation Signals (5m)",
      "type": "timeseries"
    },
    {
      "datasource": { "type": "prometheus", "uid": "${DS_PROMETHEUS}" },
      "description": "Current propagation snapshot across root and upstream metrics.",
      "fieldConfig": {
        "defaults": {
          "color": { "mode": "thresholds" },
          "mappings": [
            {
              "options": {
                "0": { "color": "green", "index": 0, "text": "Quiet" }
              },
              "type": "value"
            }
          ],
          "min": 0,
          "thresholds": {
            "mode": "absolute",
            "steps": [
              { "color": "green", "value": null },
              { "color": "yellow", "value": 0.01 },
              { "color": "red", "value": 0.05 }
            ]
          }
        },
        "overrides": []
      },
      "gridPos": { "h": 10, "w": 12, "x": 0, "y": 27 },
      "id": 6,
      "options": {
        "displayMode": "gradient",
        "minVizHeight": 10,
        "minVizWidth": 0,
        "namePlacement": "auto",
        "orientation": "horizontal",
        "reduceOptions": {
          "calcs": ["lastNotNull"],
          "fields": "",
          "values": false
        },
        "showUnfilled": true,
        "sizing": "auto"
      },
      "targets": [
        {
          "editorMode": "code",
          "expr": "rate(wallet_db_check_failures_total[5m])",
          "instant": true,
          "legendFormat": "wallet_db_check_failures_total",
          "range": false,
          "refId": "A"
        },
        {
          "editorMode": "code",
          "expr": "rate(identity_db_check_failures_total[5m])",
          "instant": true,
          "legendFormat": "identity_db_check_failures_total",
          "range": false,
          "refId": "B"
        },
        {
          "editorMode": "code",
          "expr": "rate(system_dependency_unready_total[5m])",
          "instant": true,
          "legendFormat": "system_dependency_unready_total",
          "range": false,
          "refId": "C"
        },
        {
          "editorMode": "code",
          "expr": "rate(ops_dependency_unready_total[5m])",
          "instant": true,
          "legendFormat": "ops_dependency_unready_total",
          "range": false,
          "refId": "D"
        },
        {
          "editorMode": "code",
          "expr": "rate(customer_portal_upstream_failures_total[5m])",
          "instant": true,
          "legendFormat": "customer_portal_upstream_failures_total",
          "range": false,
          "refId": "E"
        },
        {
          "editorMode": "code",
          "expr": "rate(admin_portal_upstream_failures_total[5m])",
          "instant": true,
          "legendFormat": "admin_portal_upstream_failures_total",
          "range": false,
          "refId": "F"
        }
      ],
      "title": "Propagation Snapshot Now",
      "type": "bargauge"
    },
    {
      "datasource": { "type": "prometheus", "uid": "${DS_PROMETHEUS}" },
      "description": "Table view of current propagation metrics.",
      "fieldConfig": {
        "defaults": {
          "color": { "mode": "thresholds" },
          "custom": {
            "align": "auto",
            "cellOptions": { "type": "auto" }
          }
        },
        "overrides": []
      },
      "gridPos": { "h": 10, "w": 12, "x": 12, "y": 27 },
      "id": 7,
      "options": {
        "cellHeight": "sm",
        "footer": {
          "countRows": false,
          "enablePagination": false,
          "fields": "",
          "reducer": ["sum"],
          "show": false
        },
        "showHeader": true
      },
      "targets": [
        {
          "editorMode": "code",
          "expr": "rate(wallet_db_check_failures_total[5m]) or rate(identity_db_check_failures_total[5m]) or rate(system_dependency_unready_total[5m]) or rate(ops_dependency_unready_total[5m]) or rate(customer_portal_upstream_failures_total[5m]) or rate(admin_portal_upstream_failures_total[5m])",
          "format": "table",
          "instant": true,
          "refId": "A"
        }
      ],
      "title": "Propagation Table",
      "transformations": [
        { "id": "labelsToFields", "options": { "mode": "columns" } },
        {
          "id": "organize",
          "options": {
            "excludeByName": {
              "Time": true,
              "instance": true,
              "job": true
            },
            "renameByName": {
              "Value": "rate_5m"
            }
          }
        }
      ],
      "type": "table"
    },
    {
      "datasource": { "type": "prometheus", "uid": "${DS_PROMETHEUS}" },
      "description": "Current readiness for the main user-facing and platform services, used here as a dependency impact mirror.",
      "fieldConfig": {
        "defaults": {
          "color": { "mode": "thresholds" },
          "mappings": [
            {
              "options": {
                "0": { "color": "red", "index": 0, "text": "Not Ready" },
                "1": { "color": "green", "index": 1, "text": "Ready" }
              },
              "type": "value"
            }
          ],
          "max": 1,
          "min": 0,
          "thresholds": {
            "mode": "absolute",
            "steps": [
              { "color": "red", "value": null },
              { "color": "green", "value": 1 }
            ]
          }
        },
        "overrides": []
      },
      "gridPos": { "h": 8, "w": 24, "x": 0, "y": 37 },
      "id": 8,
      "options": {
        "displayMode": "gradient",
        "minVizHeight": 10,
        "minVizWidth": 0,
        "namePlacement": "auto",
        "orientation": "horizontal",
        "reduceOptions": {
          "calcs": ["lastNotNull"],
          "fields": "",
          "values": false
        },
        "showUnfilled": true,
        "sizing": "auto"
      },
      "targets": [
        {
          "editorMode": "code",
          "expr": "max by (service) (service_ready_state{environment=~\"$environment\"})",
          "instant": true,
          "legendFormat": "{{service}}",
          "range": false,
          "refId": "A"
        }
      ],
      "title": "Current Readiness Impact Snapshot",
      "type": "bargauge"
    }
  ],
  "refresh": "15s",
  "schemaVersion": 39,
  "style": "dark",
  "tags": ["stackpilot", "m9", "phase-3", "3c", "dependency", "propagation"],
  "templating": {
    "list": [
      {
        "current": { "selected": true, "text": "dev", "value": "dev" },
        "hide": 0,
        "includeAll": false,
        "label": "environment",
        "multi": false,
        "name": "environment",
        "options": [{ "selected": true, "text": "dev", "value": "dev" }],
        "query": "dev",
        "skipUrlSync": false,
        "type": "custom"
      }
    ]
  },
  "time": { "from": "now-15m", "to": "now" },
  "timepicker": {},
  "timezone": "browser",
  "title": "M9 - 3C - Dependency and Propagation",
  "uid": "m9-3c-dependency-propagation",
  "version": 1,
  "weekStart": ""
}
